{"openapi":"3.1.0","info":{"title":"Book-Link API","version":"0.1.0"},"paths":{"/users/signup":{"post":{"tags":["users"],"summary":"Signup","operationId":"signup_users_signup_post","requestBody":{"content":{"application/json":{"schema":{"$ref":"#/components/schemas/UserCreate"}}},"required":true},"responses":{"200":{"description":"Successful Response","content":{"application/json":{"schema":{"$ref":"#/components/schemas/UserOut"}}}},"422":{"description":"Validation Error","content":{"application/json":{"schema":{"$ref":"#/components/schemas/HTTPValidationError"}}}}}}},"/users/login":{"post":{"tags":["users"],"summary":"Login","operationId":"login_users_login_post","requestBody":{"content":{"application/x-www-form-urlencoded":{"schema":{"$ref":"#/components/schemas/Body_login_users_login_post"}}},"required":true},"responses":{"200":{"description":"Successful Response","content":{"application/json":{"schema":{"$ref":"#/components/schemas/Token"}}}},"422":{"description":"Validation Error","content":{"application/json":{"schema":{"$ref":"#/components/schemas/HTTPValidationError"}}}}}}},"/users/me":{"get":{"tags":["users"],"summary":"Read Users Me","operationId":"read_users_me_users_me_get","responses":{"200":{"description":"Successful Response","content":{"application/json":{"schema":{"$ref":"#/components/schemas/UserOut"}}}}},"security":[{"OAuth2PasswordBearer":[]}]},"patch":{"tags":["users"],"summary":"Update User Me","operationId":"update_user_me_users_me_patch","requestBody":{"content":{"application/json":{"schema":{"$ref":"#/components/schemas/UserUpdate"}}},"required":true},"responses":{"200":{"description":"Successful Response","content":{"application/json":{"schema":{"$ref":"#/components/schemas/UserOut"}}}},"422":{"description":"Validation Error","content":{"application/json":{"schema":{"$ref":"#/components/schemas/HTTPValidationError"}}}}},"security":[{"OAuth2PasswordBearer":[]}]}},"/books/":{"get":{"tags":["books"],"summary":"Get Books","operationId":"get_books_books__get","responses":{"200":{"description":"Successful Response","content":{"application/json":{"schema":{"items":{"$ref":"#/components/schemas/BookOut"},"type":"array","title":"Response Get Books Books  Get"}}}}}},"post":{"tags":["books"],"summary":"Create Book","operationId":"create_book_books__post","requestBody":{"content":{"application/json":{"schema":{"$ref":"#/components/schemas/BookCreate"}}},"required":true},"responses":{"200":{"description":"Successful Response","content":{"application/json":{"schema":{"$ref":"#/components/schemas/BookOut"}}}},"422":{"description":"Validation Error","content":{"application/json":{"schema":{"$ref":"#/components/schemas/HTTPValidationError"}}}}},"security":[{"OAuth2PasswordBearer":[]}]}},"/books/{book_id}":{"get":{"tags":["books"],"summary":"Get Book","operationId":"get_book_books__book_id__get","parameters":[{"name":"book_id","in":"path","required":true,"schema":{"type":"integer","title":"Book Id"}}],"responses":{"200":{"description":"Successful Response","content":{"application/json":{"schema":{"$ref":"#/components/schemas/BookOut"}}}},"422":{"description":"Validation Error","content":{"application/json":{"schema":{"$ref":"#/components/schemas/HTTPValidationError"}}}}}}}},"components":{"schemas":{"Body_login_users_login_post":{"properties":{"grant_type":{"anyOf":[{"type":"string","pattern":"^password$"},{"type":"null"}],"title":"Grant Type"},"username":{"type":"string","title":"Username"},"password":{"type":"string","format":"password","title":"Password"},"scope":{"type":"string","title":"Scope","default":""},"client_id":{"anyOf":[{"type":"string"},{"type":"null"}],"title":"Client Id"},"client_secret":{"anyOf":[{"type":"string"},{"type":"null"}],"format":"password","title":"Client Secret"}},"type":"object","required":["username","password"],"title":"Body_login_users_login_post"},"BookCreate":{"properties":{"title":{"type":"string","title":"Title"},"author":{"type":"string","title":"Author"},"description":{"type":"string","title":"Description"},"genre":{"type":"string","title":"Genre"},"price":{"type":"number","title":"Price"},"image_url":{"anyOf":[{"type":"string"},{"type":"null"}],"title":"Image Url"}},"type":"object","required":["title","author","description","genre","price"],"title":"BookCreate"},"BookOut":{"properties":{"title":{"type":"string","title":"Title"},"author":{"type":"string","title":"Author"},"description":{"type":"string","title":"Description"},"genre":{"type":"string","title":"Genre"},"price":{"type":"number","title":"Price"},"image_url":{"anyOf":[{"type":"string"},{"type":"null"}],"title":"Image Url"},"id":{"type":"integer","title":"Id"},"owner_id":{"type":"integer","title":"Owner Id"}},"type":"object","required":["title","author","description","genre","price","id","owner_id"],"title":"BookOut"},"HTTPValidationError":{"properties":{"detail":{"items":{"$ref":"#/components/schemas/ValidationError"},"type":"array","title":"Detail"}},"type":"object","title":"HTTPValidationError"},"Token":{"properties":{"access_token":{"type":"string","title":"Access Token"},"token_type":{"type":"string","title":"Token Type"}},"type":"object","required":["access_token","token_type"],"title":"Token"},"UserCreate":{"properties":{"username":{"type":"string","title":"Username"},"email":{"type":"string","format":"email","title":"Email"},"bio":{"anyOf":[{"type":"string"},{"type":"null"}],"title":"Bio"},"password":{"type":"string","title":"Password"}},"type":"object","required":["username","email","password"],"title":"UserCreate"},"UserOut":{"properties":{"username":{"type":"string","title":"Username"},"email":{"type":"string","format":"email","title":"Email"},"bio":{"anyOf":[{"type":"string"},{"type":"null"}],"title":"Bio"},"id":{"type":"integer","title":"Id"},"profile_image":{"anyOf":[{"type":"string"},{"type":"null"}],"title":"Profile Image"}},"type":"object","required":["username","email","id"],"title":"UserOut"},"UserUpdate":{"properties":{"username":{"anyOf":[{"type":"string"},{"type":"null"}],"title":"Username"},"email":{"anyOf":[{"type":"string","format":"email"},{"type":"null"}],"title":"Email"},"bio":{"anyOf":[{"type":"string"},{"type":"null"}],"title":"Bio"},"profile_image":{"anyOf":[{"type":"string"},{"type":"null"}],"title":"Profile Image"}},"type":"object","title":"UserUpdate"},"ValidationError":{"properties":{"loc":{"items":{"anyOf":[{"type":"string"},{"type":"integer"}]},"type":"array","title":"Location"},"msg":{"type":"string","title":"Message"},"type":{"type":"string","title":"Error Type"}},"type":"object","required":["loc","msg","type"],"title":"ValidationError"}},"securitySchemes":{"OAuth2PasswordBearer":{"type":"oauth2","flows":{"password":{"scopes":{},"tokenUrl":"users/login"}}}}}}